oncvideo/__init__.py
oncvideo/__main__.py
oncvideo/_arg_parser.py
oncvideo/_iterate_ffmpeg.py
oncvideo/_utils.py
oncvideo/didson_file.py
oncvideo/dives_onc.py
oncvideo/download_files.py
oncvideo/extract_frame.py
oncvideo/list_files.py
oncvideo/seatube.py
oncvideo/timelapse.py
oncvideo/ts_download.py
oncvideo/utils.py
oncvideo/video_info.py
oncvideo-1.4.dist-info/licenses/LICENSE
oncvideo-1.4.dist-info/METADATA
oncvideo-1.4.dist-info/WHEEL
oncvideo-1.4.dist-info/entry_points.txt
oncvideo-1.4.dist-info/top_level.txt
oncvideo-1.4.dist-info/RECORD
