Metadata-Version: 2.4
Name: oncvideo
Version: 1.4
Summary: A collection of commands to help get archived videos from Oceans 3.
Author-email: Paulo Correa <pcorrea@oceannetworks.ca>
License-Expression: MIT
Project-URL: Repository, https://github.com/correapvf/oncvideo
Classifier: Development Status :: 4 - Beta
Classifier: Programming Language :: Python :: 3
Classifier: Intended Audience :: Science/Research
Classifier: Topic :: Scientific/Engineering :: Oceanography
Requires-Python: >=3.10
License-File: LICENSE
Requires-Dist: pandas
Requires-Dist: requests
Requires-Dist: tqdm
Requires-Dist: onc
Requires-Dist: backoff
Requires-Dist: ffmpeg_progress_yield
Requires-Dist: opencv-python
Requires-Dist: ttf_opensans
Dynamic: license-file
